elwood/__init__.py
elwood/cli.py
elwood/constants.py
elwood/download.py
elwood/elwood.py
elwood/feature_normalization.py
elwood/feature_scaling.py
elwood/file_processor.py
elwood/geo_processor.py
elwood/normalizer.py
elwood/standardizer.py
elwood/time_helpers.py
elwood/time_processor.py
elwood/utils.py
elwood/data/iso_lookup.csv
elwood/transformations/__init__.py
elwood/transformations/clipping.py
elwood/transformations/geo_utils.py
elwood/transformations/outlier_scaling.py
elwood/transformations/regridding.py
elwood/transformations/regridding_2.py
elwood/transformations/scaling.py
elwood/transformations/temporal_utils.py
elwood/transformations/test.py
elwood-0.1.4.dist-info/AUTHORS.md
elwood-0.1.4.dist-info/LICENSE
elwood-0.1.4.dist-info/METADATA
elwood-0.1.4.dist-info/WHEEL
elwood-0.1.4.dist-info/entry_points.txt
elwood-0.1.4.dist-info/top_level.txt
elwood-0.1.4.dist-info/RECORD
