Metadata-Version: 2.1
Name: elwood
Version: 0.1.4
Summary: An open source dataset transformation, standardization, and normalization python library.
Home-page: https://github.com/jataware/elwood
Author: Brandon Rose, Powell Fendley
Author-email: info@jataware.com
License: MIT license
Keywords: elwood
Platform: UNKNOWN
Classifier: Development Status :: 2 - Pre-Alpha
Classifier: Intended Audience :: Developers
Classifier: License :: OSI Approved :: MIT License
Classifier: Natural Language :: English
Classifier: Programming Language :: Python :: 3
Classifier: Programming Language :: Python :: 3.8
Classifier: Programming Language :: Python :: 3.9
Classifier: Programming Language :: Python :: 3.10
Requires-Python: >=3.8
License-File: LICENSE
License-File: AUTHORS.md
Requires-Dist: bump2version (==1.0.1)
Requires-Dist: cdo (==1.5.7)
Requires-Dist: Click (==8.0)
Requires-Dist: coverage (==4.5.4)
Requires-Dist: Cython (==0.29.23)
Requires-Dist: flake8 (==3.7.8)
Requires-Dist: fuzzywuzzy (==0.18.0)
Requires-Dist: GDAL (==3.3.2)
Requires-Dist: geofeather (>=0.3.0)
Requires-Dist: geopandas (==0.8.1)
Requires-Dist: netCDF4 (==1.5.3)
Requires-Dist: numpy (<=1.24.3)
Requires-Dist: openpyxl (==3.0.7)
Requires-Dist: pandas (==1.5.3)
Requires-Dist: pip (>=21.1)
Requires-Dist: pydantic (>=1.8.2)
Requires-Dist: pyproj (<=3.5)
Requires-Dist: python-Levenshtein (>=0.12.2)
Requires-Dist: rioxarray (==0.13.4)
Requires-Dist: Rtree (==0.8.3)
Requires-Dist: setuptools (<58)
Requires-Dist: shapely (==2.0.1)
Requires-Dist: Sphinx (==1.8.5)
Requires-Dist: tox (==3.14.0)
Requires-Dist: tqdm (<5.0.0,>=4.41.1)
Requires-Dist: twine (==1.14.0)
Requires-Dist: watchdog (==0.9.0)
Requires-Dist: wheel (==0.33.6)
Requires-Dist: xarray (==0.19.0)
Requires-Dist: xlrd (==2.0.1)
